{
  "run": {
    "command": "nx build @pesto-ui/components-layout",
    "startTime": "2024-12-17T14:26:01.912Z",
    "endTime": "2024-12-17T14:26:11.218Z",
    "inner": false
  },
  "tasks": [
    {
      "taskId": "@pesto-ui/esbulid-config:build",
      "target": "build",
      "projectName": "@pesto-ui/esbulid-config",
      "hash": "9590364390923102752",
      "startTime": "2024-12-17T14:26:01.950Z",
      "endTime": "2024-12-17T14:26:01.952Z",
      "params": "",
      "cacheStatus": "local-cache-hit",
      "status": 0
    },
    {
      "taskId": "@pesto-ui/themes:build",
      "target": "build",
      "projectName": "@pesto-ui/themes",
      "hash": "8729752136303659095",
      "startTime": "2024-12-17T14:26:01.954Z",
      "endTime": "2024-12-17T14:26:01.964Z",
      "params": "",
      "cacheStatus": "local-cache-hit",
      "status": 0
    },
    {
      "taskId": "@pesto-ui/components-layout:build",
      "target": "build",
      "projectName": "@pesto-ui/components-layout",
      "hash": "2833708374004955917",
      "startTime": "2024-12-17T14:26:01.968Z",
      "endTime": "2024-12-17T14:26:11.179Z",
      "params": "",
      "cacheStatus": "cache-miss",
      "status": 0
    }
  ]
}